onlysq/__init__.py
onlysq/asnc.py
onlysq/sync.py
onlysq-0.0.1.dist-info/METADATA
onlysq-0.0.1.dist-info/WHEEL
onlysq-0.0.1.dist-info/top_level.txt
onlysq-0.0.1.dist-info/RECORD
